MANIFEST.in
README.rst
setup.py
aliyun_python_sdk_eci.egg-info/PKG-INFO
aliyun_python_sdk_eci.egg-info/SOURCES.txt
aliyun_python_sdk_eci.egg-info/dependency_links.txt
aliyun_python_sdk_eci.egg-info/requires.txt
aliyun_python_sdk_eci.egg-info/top_level.txt
aliyunsdkeci/__init__.py
aliyunsdkeci/request/__init__.py
aliyunsdkeci/request/v20180808/CommitContainerRequest.py
aliyunsdkeci/request/v20180808/CopyDataCacheRequest.py
aliyunsdkeci/request/v20180808/CreateContainerGroupRequest.py
aliyunsdkeci/request/v20180808/CreateDataCacheRequest.py
aliyunsdkeci/request/v20180808/CreateImageCacheRequest.py
aliyunsdkeci/request/v20180808/DeleteContainerGroupRequest.py
aliyunsdkeci/request/v20180808/DeleteContainerGroupsRequest.py
aliyunsdkeci/request/v20180808/DeleteDataCacheRequest.py
aliyunsdkeci/request/v20180808/DeleteImageCacheRequest.py
aliyunsdkeci/request/v20180808/DescribeAvailableResourceRequest.py
aliyunsdkeci/request/v20180808/DescribeCommitContainerTaskRequest.py
aliyunsdkeci/request/v20180808/DescribeContainerGroupEventsRequest.py
aliyunsdkeci/request/v20180808/DescribeContainerGroupMetricRequest.py
aliyunsdkeci/request/v20180808/DescribeContainerGroupPriceRequest.py
aliyunsdkeci/request/v20180808/DescribeContainerGroupStatusRequest.py
aliyunsdkeci/request/v20180808/DescribeContainerGroupsRequest.py
aliyunsdkeci/request/v20180808/DescribeContainerLogRequest.py
aliyunsdkeci/request/v20180808/DescribeDataCachesRequest.py
aliyunsdkeci/request/v20180808/DescribeImageCachesRequest.py
aliyunsdkeci/request/v20180808/DescribeMultiContainerGroupMetricRequest.py
aliyunsdkeci/request/v20180808/DescribeRegionsRequest.py
aliyunsdkeci/request/v20180808/ExecContainerCommandRequest.py
aliyunsdkeci/request/v20180808/ListUsageRequest.py
aliyunsdkeci/request/v20180808/ResizeContainerGroupEphemeralStorageRequest.py
aliyunsdkeci/request/v20180808/ResizeContainerGroupVolumeRequest.py
aliyunsdkeci/request/v20180808/RestartContainerGroupRequest.py
aliyunsdkeci/request/v20180808/UpdateContainerGroupRequest.py
aliyunsdkeci/request/v20180808/UpdateDataCacheRequest.py
aliyunsdkeci/request/v20180808/UpdateImageCacheRequest.py
aliyunsdkeci/request/v20180808/__init__.py